{
    "sgc": false,
    "sfy": false,
    "qfy": false,
    "transUser": {
        "id": 11382277,
        "status": 99,
        "demand": 1,
        "userid": 124033720,
        "nickname": "拿不拿的男友Rin",
        "uptime": 1595215166307
    },
    "lrc": {
        "version": 58,
        "lyric": "{\"t\":0,\"c\":[{\"tx\":\"作词: \"},{\"tx\":\"Ayase\",\"li\":\"http://p1.music.126.net/dYKRaT9i53is2sGfLO2QcQ==/109951165253432028.jpg\",\"or\":\"orpheus://nm/artist/home?id=35135807&type=artist\"}]}\n{\"t\":729,\"c\":[{\"tx\":\"作曲: \"},{\"tx\":\"Ayase\",\"li\":\"http://p1.music.126.net/dYKRaT9i53is2sGfLO2QcQ==/109951165253432028.jpg\",\"or\":\"orpheus://nm/artist/home?id=35135807&type=artist\"}]}\n{\"t\":1458,\"c\":[{\"tx\":\"编曲: \"},{\"tx\":\"Ayase\",\"li\":\"http://p1.music.126.net/dYKRaT9i53is2sGfLO2QcQ==/109951165253432028.jpg\",\"or\":\"orpheus://nm/artist/home?id=35135807&type=artist\"}]}\n[00:02.187]涙流すことすら無いまま\n[00:07.437]過ごした日々の痕一つも残さずに\n[00:16.805]さよならだ\n[00:23.438]一人で迎えた朝に\n[00:26.411]鳴り響く誰かの音\n[00:28.961]二人で過ごした部屋で\n[00:31.594]目を閉じたまま考えてた\n[00:34.360]悪いのは誰だ\n[00:38.394]分かんないよ\n[00:39.827]誰のせいでもない\n[00:43.394]たぶん\n[00:44.227]僕らは何回だってきっと\n[00:47.210]そう何年だってきっと\n[00:50.127]さよならと共に終わるだけなんだ\n[00:55.427]仕方がないよきっと\n[00:57.928]\"おかえり\"\n[00:58.877]思わず零れた言葉は\n[01:03.027]違うな\n[01:14.260]一人で迎えた朝に\n[01:16.944]ふと想う誰かのこと\n[01:19.610]二人で過ごした日々の\n[01:22.260]当たり前がまだ残っている\n[01:25.027]悪いのは君だ\n[01:29.111]そうだっけ\n[01:30.295]悪いのは僕だ\n[01:34.278]たぶん\n[01:35.495]これも大衆的恋愛でしょ\n[01:38.295]それは最終的な答えだよ\n[01:40.578]僕らだんだんとズレていったの\n[01:43.311]それもただよくある聴き慣れたストーリーだ\n[01:46.995]あんなに輝いていた日々にすら\n[01:51.456]埃は積もっていくんだ\n[01:55.697]僕らは何回だってきっと\n[01:59.447]そう何年だってきっと\n[02:02.030]さよならに続く道を歩くんだ\n[02:07.382]仕方がないよきっと\n[02:09.796]\"おかえり\"\n[02:11.063]いつもの様に\n[02:13.663]零れ落ちた\n[02:34.396]分かり合えないことなんてさ\n[02:36.781]幾らでもあるんだきっと\n[02:39.097]全てを許し合えるわけじゃないから\n[02:44.663]ただ 優しさの日々を\n[02:47.047]辛い日々と感じてしまったのなら\n[02:51.031]戻れないから\n[02:57.619]僕らは何回だってきっと\n[03:00.320]僕らは何回だってきっと\n[03:03.388]そう何年だってきっと\n[03:05.903]さよならと共に終わるだけなんだ\n[03:11.320]仕方がないよきっと\n[03:14.006]\"おかえり\"\n[03:14.888]思わず零れた言葉は\n[03:18.902]違うな\n[03:21.051]それでも何回だってきっと\n[03:24.387]そう何年だってきっと\n[03:27.152]始まりに戻ることが出来たなら\n[03:32.668]なんて思ってしまうよ\n[03:35.387]\"おかえり\"\n[03:36.268]届かず零れた言葉に\n[03:40.268]笑った\n[03:42.768]少し冷えた朝だ\n[03:48.835]\n"
    },
    "klyric": {
        "version": 0,
        "lyric": ""
    },
    "tlyric": {
        "version": 16,
        "lyric": "[00:02.187]就连眼泪也没能流下\n[00:07.437]与你一起度过的日子没有留下一丝痕迹\n[00:16.805]再见了\n[00:23.438]一个人迎来早晨\n[00:26.411]传来了某人发出的声响\n[00:28.961]躺在我们曾生活过的房间里\n[00:31.594]闭上眼思考着\n[00:34.360]到底是谁的错\n[00:38.394]我不知道啊\n[00:39.827]或许我们都没有错吧\n[00:43.394]大概\n[00:44.227]无论多少次  我们都一定只会\n[00:47.210]没错  无论过多少年都一定只会\n[00:50.127]与一句再见一同走向结局\n[00:55.427]肯定没有办法的啊\n[00:57.928]「欢迎回来」\n[00:58.877]脱口而出的这句话\n[01:03.027]果然还是说错了啊\n[01:14.260]一个人迎来清晨\n[01:16.944]突然想起了某人\n[01:19.610]两人一起度过的日子中的平凡琐事\n[01:22.260]仍然还残留着未曾消失\n[01:25.027]是你的错啊\n[01:29.111]是这样的吗\n[01:30.295]或许是我的错啊\n[01:34.278]或许是这样\n[01:35.495]这也算是普遍的恋爱嘛\n[01:38.295]那就是我得出的最终答案\n[01:40.578]我们渐渐偏离了轨道\n[01:43.311]不过那也只是经常听到的故事罢了\n[01:46.995]就连曾经那样灿烂的日子\n[01:51.456]也会积上灰尘的啊\n[01:55.697]无论多少次  我们都一定会\n[01:59.447]没错  无论过多少年都一定会\n[02:02.030]走上通往离别的道路\n[02:07.382]肯定没有办法的啊\n[02:09.796]「欢迎回来」\n[02:11.063]像往常一般\n[02:13.663]脱口而出\n[02:34.396]无法互相理解的事情\n[02:36.781]肯定是数不胜数的\n[02:39.097]因为并不是所有事都能够互相原谅\n[02:44.663]但是  一旦那些温柔的时光\n[02:47.047]让人感到无比煎熬的话\n[02:51.031]就已经回不去了\n[02:57.619]无论多少次  我们都一定只会\n[03:00.320]无论多少次  我们都一定只会\n[03:03.388]没错、无论过多少年都一定只会\n[03:05.903]与一句再见一同走向结局\n[03:11.320]肯定没有办法的啊\n[03:14.006]「欢迎回来」\n[03:14.888]脱口而出的这句话\n[03:18.902]果然还是说错了啊\n[03:21.051]即便如此  无论多少次都一定会\n[03:24.387]没错  无论过多少年都一定会\n[03:27.152]不经意的去想\n[03:32.668]要是能回到我们开始的时候就好了\n[03:35.387]「欢迎回来」\n[03:36.268]脱口而出的这句话没法传达给你\n[03:40.268]我只能苦笑着\n[03:42.768]迎来略带凉意的早晨\n[03:48.835]"
    },
    "romalrc": {
        "version": 6,
        "lyric": "[00:02.187]na mi da na ga su ko to su ra na i ma ma\n[00:07.437]su go shi ta hi bi no a to hi to tsu mo no ko sa zu ni\n[00:16.805]sa yo na ra da\n[00:23.438]hi to ri de mu ka e ta a sa ni\n[00:26.411]na ri hi bi ku da re ka no o to\n[00:28.961]fu ta ri de su go shi ta he ya de\n[00:31.594]me wo to ji ta ma ma ka n ga e te ta\n[00:34.360]wa ru i no wa da re da\n[00:38.394]wa ka n na i yo\n[00:39.827]da re no se i de mo na i\n[00:43.394]ta bu n\n[00:44.227]bo ku ra wa na n ka i da tte ki tto\n[00:47.210]so u na n ne n da tte ki tto\n[00:50.127]sa yo na ra to to mo ni o wa ru da ke na n da\n[00:55.427]shi ka ta ga na i yo ki tto\n[00:57.928]\"o ka e ri\"\n[00:58.877]o mo wa zu ko bo re ta ko to ba wa\n[01:03.027]chi ga u na\n[01:14.260]hi to ri de mu ka e ta a sa ni\n[01:16.944]fu to o mo u da re ka no ko to\n[01:19.610]fu ta ri de su go shi ta hi bi no\n[01:22.260]a ta ri ma e ga ma da no ko tte i ru\n[01:25.027]wa ru i no wa ki mi da\n[01:29.111]so u da kke\n[01:30.295]wa ru i no wa bo ku da\n[01:34.278]ta bu n\n[01:35.495]ko re mo ta i shu u te ki re n'a i de sho\n[01:38.295]so re wa sa i shu u te ki na ko ta e da yo\n[01:40.578]bo ku ra da n da n to zu re te i tta no\n[01:43.311]so re mo ta da yo ku a ru ki ki na re ta su too rii da\n[01:46.995]a n na ni ka ga ya i te i ta hi bi ni su ra\n[01:51.456]ho ko ri wa tsu mo tte i ku n da\n[01:55.697]bo ku ra wa na n ka i da tte ki tto\n[01:59.447]so u na n ne n da tte ki tto\n[02:02.030]sa yo na ra ni tsu zu ku mi chi wo a ru ku n da\n[02:07.382]shi ka ta ga na i yo ki tto\n[02:09.796]\"o ka e ri\"\n[02:11.063]i tsu mo no yo u ni\n[02:13.663]ko bo re o chi ta\n[02:34.396]wa ka ri a e na i ko to na n te sa\n[02:36.781]i ku ra de mo a ru n da ki tto\n[02:39.097]su be te wo yu ru shi a e ru wa ke ja na i ka ra\n[02:44.663]ta da ya sa shi sa no hi bi wo\n[02:47.047]tsu ra i hi bi to ka n ji te shi ma tta no na ra\n[02:51.031]mo do re na i ka ra\n[02:57.619]bo ku ra wa na n ka i da tte ki tto\n[03:00.320]bo ku ra wa na n ka i da tte ki tto\n[03:03.388]so u na n ne n da tte ki tto\n[03:05.903]sa yo na ra to to mo ni o wa ru da ke na n da\n[03:11.320]shi ka ta ga na i yo ki tto\n[03:14.006]\"o ka e ri\"\n[03:14.888]o mo wa zu ko bo re ta ko to ba wa\n[03:18.902]chi ga u na\n[03:21.051]so re de mo na n ka i da tte ki tto\n[03:24.387]so u na n ne n da tte ki tto\n[03:27.152]ha ji ma ri ni mo do ru ko to ga de ki ta na ra\n[03:32.668]na n te o mo tte shi ma u yo\n[03:35.387]\"o ka e ri\"\n[03:36.268]to do ka zu ko bo re ta ko to ba ni\n[03:40.268]wa ra tta\n[03:42.768]su ko shi hi e ta a sa da\n[03:48.835]"
    },
    "code": 200
}